{
	"title": {
		"type": "plain_text",
		"text": "Salesforce Health Cloud",
		"emoji": true
	},
	"submit": {
		"type": "plain_text",
		"text": "Submit",
		"emoji": true
	},
	"type": "modal",
	"close": {
		"type": "plain_text",
		"text": "Cancel",
		"emoji": true
	},
	"blocks": [
		{
			"type": "input",
			"element": {
				"type": "static_select",
				"placeholder": {
					"type": "plain_text",
					"text": "Select medication",
					"emoji": true
				},
				"options": [
					{
						"text": {
							"type": "plain_text",
							"text": "NovoLog Mix 70/30",
							"emoji": true
						},
						"value": "value-0"
					},
					{
						"text": {
							"type": "plain_text",
							"text": "Ryzodeg",
							"emoji": true
						},
						"value": "value-1"
					},
					{
						"text": {
							"type": "plain_text",
							"text": "Kombiglyze XR",
							"emoji": true
						},
						"value": "value-2"
					}
				],
				"action_id": "static_select-action"
			},
			"label": {
				"type": "plain_text",
				"text": "Assign Medication",
				"emoji": true
			}
		}
	]
}